{"title":"六便士茶坊","subtitle":null,"description":null,"author":"Zauruso","language":"zh-CN","timezone":"Asia/Shanghai","url":"https://zauruso.coding.me","root":"/","permalink":"posts/:abbrlink/","permalink_defaults":null,"source_dir":"source","public_dir":"public","tag_dir":"tags","archive_dir":"archives","category_dir":"categories","code_dir":"downloads/code","i18n_dir":":lang","skip_render":null,"new_post_name":":title.md","default_layout":"post","titlecase":false,"external_link":true,"filename_case":0,"render_drafts":false,"post_asset_folder":true,"relative_link":false,"future":true,"highlight":{"enable":true,"auto_detect":true,"line_number":true,"tab_replace":null,"first_line_number":"always1"},"default_category":"categorized","category_map":["报错指南"],"tag_map":null,"date_format":"YYYY-MM-DD","time_format":"HH:mm:ss","per_page":10,"pagination_dir":"page","theme":"pure","deploy":[{"type":"git","repository":null,"repo":{"github":"git@github.com:zauruso/zauruso.github.io.git,master","coding":"git@git.coding.net:zauruso/zauruso.coding.me.git,master"}},{"type":"baidu_url_submitter"}],"ignore":[],"githubEmojis":{"enable":true,"idName":"github-emoji","unicode":false,"styles":null,"localEmojis":null},"archive_generator":{"per_page":20,"yearly":true,"monthly":true,"daily":true},"category_generator":{"per_page":0},"tag_generator":{"per_page":0},"abbrlink":{"alg":"crc32","rep":"dec"},"index_generator":{"per_page":10,"order_by":"-date","path":""},"neat_enable":true,"neat_html":{"enable":true,"exclude":null,"ignoreCustomComments":[{}],"removeComments":true,"removeCommentsFromCDATA":true,"collapseWhitespace":true,"collapseBooleanAttributes":true,"removeEmptyAttributes":true,"html5":true,"includeAutoGeneratedTags":true,"ignoreCustomFragments":[{},{}]},"neat_css":{"enable":true,"exclude":["*.min.css"]},"neat_js":{"enable":true,"mangle":true,"output":null,"compress":null,"exclude":["*.min.js"],"fromString":true},"jsonContent":{"meta":false,"pages":false,"posts":{"title":true,"date":true,"path":true,"text":true,"raw":false,"content":true,"slug":false,"updated":false,"comments":false,"link":false,"permalink":true,"excerpt":false,"categories":true,"tags":true,"ignore":["path/to/a/page","url/to/one/post","an-entire-category","specific.file",".ext"]}},"search":{"insight":true,"swiftype":null,"baidu":false},"Plugins":["hexo-generator-baidu-sitemap","hexo-generator-sitemap"],"sitemap":{"path":"sitemap.xml"},"baidusitemap":{"path":"baidusitemap.xml"},"feed":{"type":"atom","limit":20,"hub":null,"content":null,"content_limit":140,"content_limit_delim":"","path":"atom.xml"},"markdown_it_plus":{"highlight":true,"html":true,"xhtmlOut":true,"breaks":true,"langPrefix":null,"linkify":true,"typographer":null,"quotes":"“”‘’","plugins":[{"plugin":{"name":"markdown-it-katex","enable":true}},{"plugin":{"name":"markdown-it-mark","enable":true}}]},"baidu_url_submit":{"count":5,"host":"https://zauruso.coding.me","token":"BE45049B-BB21-5871-8794-E6289C61938C","path":"baidu_urls.txt"},"server":{"port":4000,"log":false,"ip":"0.0.0.0","compress":false,"header":true},"menu":{"Home":".","Archives":"archives","Categories":"categories","Tags":"tags"},"menu_icons":{"enable":true,"home":"icon-home-fill","archives":"icon-archives-fill","categories":"icon-folder","tags":"icon-tags","links":"icon-friendship"},"rss":"/atom.xml","site":{"logo":{"enabled":true,"width":40,"height":40,"url":"../images/logo.png"},"title":"六便士茶坊","favicon":"/favicon.bmp","board":"<p> —————————————<br />———————</p>","copyright":false},"config":{"skin":null,"layout":"main-center","toc":true,"menu_highlight":true,"thumbnail":false,"excerpt_link":"Read More"},"pagination":{"number":false,"prev":{"alwayShow":true},"next":{"alwayShow":true}},"sidebar":"right","widgets":["board","category","tag","tagcloud","archive","recent_posts"],"index_widgets":["category","tagcloud"],"archive_type":"monthly","show_count":true,"donate":{"enable":false,"weipay":{"image":"images/donate/weipay.jpg","qrcode":"images/donate/weipayimg.png","title":"微信支付"},"alipay":{"image":"images/donate/alipay.jpg","qrcode":"images/donate/alipayimg.png","title":"支付宝"}},"share":{"enable":true,"sites":"weibo,qq,wechat,facebook,twitter","mobile_sites":"weibo,qq,qzone"},"github":{"username":"zauruso"},"comment":{"type":null,"disqus":null,"youyan":{"uid":null},"livere":{"uid":null},"gitment":{"githubID":null,"repo":null,"ClientID":null,"ClientSecret":null,"lazy":false}},"pv":{"busuanzi":{"enable":true},"leancloud":{"enable":false,"app_id":null,"app_key":null}},"postCount":{"enable":true,"wordcount":true,"min2read":false},"plugins":{"google_analytics":null,"google_site_verification":null,"baidu_analytics":null,"tencent_analytics":null},"twitter":null,"google_plus":null,"fb_admins":null,"fb_app_id":null,"profile":{"enabled":true,"avatar":"images/avatar.jpg","gravatar":null,"author":"zauruso","author_description":"好好学习，天天向上","location":"China","follow":"https://zauruso.github.io/","social":{"links":{"github":"https://github.com/zauruso","rss":"atom.xml"},"link_tooltip":true},"links":{"Github":"https://github.com/zauruso"}}}